omaslib/__init__.py
omaslib/ontologies/admin.trig
omaslib/ontologies/omas.shacl.trig
omaslib/ontologies/omas.ttl
omaslib/src/__init__.py
omaslib/src/connection.py
omaslib/src/datamodel.py
omaslib/src/dtypes/__init__.py
omaslib/src/dtypes/bnode.py
omaslib/src/dtypes/languagein.py
omaslib/src/dtypes/namespaceiri.py
omaslib/src/dtypes/rdfset.py
omaslib/src/dtypes/xsdset.py
omaslib/src/enums/__init__.py
omaslib/src/enums/action.py
omaslib/src/enums/language.py
omaslib/src/enums/permissions.py
omaslib/src/enums/permissionsetattr.py
omaslib/src/enums/propertyclassattr.py
omaslib/src/enums/resourceclassattr.py
omaslib/src/enums/sparql_result_format.py
omaslib/src/enums/userdataclassattr.py
omaslib/src/enums/xsd_datatypes.py
omaslib/src/helpers/Notify.py
omaslib/src/helpers/__init__.py
omaslib/src/helpers/context.py
omaslib/src/helpers/langstring.py
omaslib/src/helpers/observable_dict.py
omaslib/src/helpers/observable_set.py
omaslib/src/helpers/omaserror.py
omaslib/src/helpers/propertyclass_singleton.py
omaslib/src/helpers/query_processor.py
omaslib/src/helpers/semantic_version.py
omaslib/src/helpers/serializer.py
omaslib/src/helpers/tools.py
omaslib/src/iconnection.py
omaslib/src/in_project.py
omaslib/src/model.py
omaslib/src/permissionset.py
omaslib/src/project.py
omaslib/src/propertyclass.py
omaslib/src/resourceclass.py
omaslib/src/user.py
omaslib/src/user_dataclass.py
omaslib/src/xsd/__init__.py
omaslib/src/xsd/floatingpoint.py
omaslib/src/xsd/iri.py
omaslib/src/xsd/xsd.py
omaslib/src/xsd/xsd_anyuri.py
omaslib/src/xsd/xsd_base64binary.py
omaslib/src/xsd/xsd_boolean.py
omaslib/src/xsd/xsd_byte.py
omaslib/src/xsd/xsd_date.py
omaslib/src/xsd/xsd_datetime.py
omaslib/src/xsd/xsd_datetimestamp.py
omaslib/src/xsd/xsd_decimal.py
omaslib/src/xsd/xsd_double.py
omaslib/src/xsd/xsd_duration.py
omaslib/src/xsd/xsd_float.py
omaslib/src/xsd/xsd_gday.py
omaslib/src/xsd/xsd_gmonth.py
omaslib/src/xsd/xsd_gmonthday.py
omaslib/src/xsd/xsd_gyear.py
omaslib/src/xsd/xsd_gyearmonth.py
omaslib-0.1.14.dist-info/METADATA
omaslib-0.1.14.dist-info/WHEEL
omaslib-0.1.14.dist-info/RECORD
