Metadata-Version: 2.1
Name: omaslib
Version: 0.1.14
Summary: Open Media Access Server Library (Linked Open Data middleware/RESTApi)
License: GNU Affero General Public License version 3
Author: Lukas Rosenthaler
Author-email: lukas.rosenthaler@unibas.ch
Requires-Python: >=3.12,<4.0
Classifier: License :: Other/Proprietary License
Classifier: Programming Language :: Python :: 3
Classifier: Programming Language :: Python :: 3.12
Requires-Dist: bcrypt (>=4.1.2,<5.0.0)
Requires-Dist: coverage (>=7.4.3,<8.0.0)
Requires-Dist: isodate (>=0.6.1,<0.7.0)
Requires-Dist: lazydocs (>=0.4.8,<0.5.0)
Requires-Dist: mkdocs (>=1.5.3,<2.0.0)
Requires-Dist: mkdocs-material (>=9.5.18,<10.0.0)
Requires-Dist: mkdocstrings (>=0.24.0,<0.25.0)
Requires-Dist: mkdocstrings-python (>=1.8.0,<2.0.0)
Requires-Dist: pyjwt (>=2.8.0,<3.0.0)
Requires-Dist: pyshacl (>=0.25.0,<0.26.0)
Requires-Dist: pystrict (>=1.3,<2.0)
Requires-Dist: rdflib (>=7.0.0,<8.0.0)
Requires-Dist: requests (>=2.31.0,<3.0.0)
Requires-Dist: setuptools (>=69.0.3,<70.0.0)
Requires-Dist: validators (>=0.22.0,<0.23.0)
Requires-Dist: xmlschema (>=3.0.1,<4.0.0)
